{"wantWatch":[],"watching":[{"title":"BanG Dream! 少女乐团派对！","type":"游戏","cover":"https://img.noobzone.ru/getimg.php?url=https://lain.bgm.tv/r/400/pic/cover/l/b2/00/208415_9u4eO.jpg","totalCount":0,"id":208415,"score":7.4,"des":"「BanG Dream!（バンドリ！）」がリズムゲームになって登場！...","collect":1567,"myStars":7,"myComment":null,"progress":0,"tags":"音游","ep_status":0},{"title":"学园偶像大师","type":"游戏","cover":"https://img.noobzone.ru/getimg.php?url=https://lain.bgm.tv/r/400/pic/cover/l/5e/2d/482314_p2UWW.jpg","totalCount":0,"id":482314,"score":7.2,"des":"2024年に誕生した、『アイドルマスター』シリーズの最新作。\r\nプレイヤーはアイドル養成学校『初星学園』に入学し、プロデューサーとして様々な問題と魅力を抱えたアイドル候補生たちをプロデュースします。\r\nアイドル養成学校『初星学園』に入学して...","collect":673,"myStars":7,"myComment":null,"progress":0,"tags":"偶像大师","ep_status":0},{"title":"蔚蓝档案","type":"游戏","cover":"https://img.noobzone.ru/getimg.php?url=https://lain.bgm.tv/r/400/pic/cover/l/4a/27/300648_Hfr75.jpg","totalCount":0,"id":300648,"score":7.3,"des":"分佈在學園城市各個地區的<學園>\r\n基本上被認定爲獨立的行政自治區域。\r\n\r\n由總管理奇普托斯的\r\n一種聯邦政府的總學生會\r\n管理並控制<學園>的構造。\r\n但是由於總學生會長突然地失蹤，\r\n總學生會陷入癱瘓的狀態，\r\n倚靠總學生會長超乎常人...","collect":2586,"myStars":7,"myComment":null,"progress":0,"tags":"手游","ep_status":0}],"watched":[]}